Metadata-Version: 1.0
Name: gauss-bio-dist
Version: 1.5
Summary: Gaussian and Binomial distributions
Home-page: UNKNOWN
Author: Ensiyeh Raoufi
Author-email: raoufien@gmail.com
License: UNKNOWN
Platform: UNKNOWN
